[
  {
    "timestamp": "2026-06-08T21:51:58.387231",
    "approved": true,
    "score": 95,
    "samenvatting": "Post voldoet aan alle vijf regels en is perfect in lijn met MIKKIE WORLD.",
    "text_preview": "Mikkie en zijn vader ontdekken vandaag een geheime grot in het bos. Durf jij ook op avontuur? Pak je"
  },
  {
    "timestamp": "2026-06-08T21:52:16.116604",
    "approved": false,
    "score": 5,
    "samenvatting": "Post geblokkeerd vanwege COPPA-schending, negatieve toon en manipulatieve verkoopdruk.",
    "text_preview": "Kinderen die niet buiten spelen zijn dom. Stuur ons je naam en leeftijd! Koop nu anders mis je het! "
  }
]